physquirrel/__init__.py
physquirrel/dnetwork.py
physquirrel/load_data.py
physquirrel/msa.py
physquirrel/quarnet.py
physquirrel/quarnetset.py
physquirrel/sdnetwork.py
physquirrel/splits.py
physquirrel/trinet.py
physquirrel/trinetset.py
physquirrel/utils/__init__.py
physquirrel/utils/_config.py
physquirrel/utils/circular.py
physquirrel/utils/mixed_graph.py
physquirrel/utils/partition.py
physquirrel/utils/tools.py
physquirrel-1.0.6.dist-info/LICENSE
physquirrel-1.0.6.dist-info/METADATA
physquirrel-1.0.6.dist-info/WHEEL
physquirrel-1.0.6.dist-info/top_level.txt
physquirrel-1.0.6.dist-info/RECORD
