Metadata-Version: 2.1
Name: physquirrel
Version: 1.0.6
Summary: package for reconstructing semi-directed phylogenetic level-1 networks from four-leaved networks and sequence alignments
Home-page: https://github.com/nholtgrefe/squirrel/tree/main/physquirrel
Author: N. Holtgrefe
Author-email: "N. Holtgrefe" <n.a.l.holtgrefe@tudelft.nl>
Classifier: License :: OSI Approved :: MIT License
Requires-Python: >=3.7
License-File: LICENSE
Requires-Dist: numpy >=2.0
Requires-Dist: networkx >=3.0
Requires-Dist: matplotlib >=3.7
Requires-Dist: scipy >=1.14
